{"cameraMode":{"drawMode":0,"name":"Shaded","section":"Shading Mode"},"sceneLighting":true,"audioPlay":false,"sceneViewState":{"showFog":true,"showMaterialUpdate":false,"showSkybox":true,"showFlares":true,"showImageEffects":true,"showParticleSystems":true},"in2DMode":false,"pivot":{"x":-10.267244338989258,"y":-14.27351188659668,"z":-6.209856986999512},"rotation":{"x":0.27250006794929507,"y":-0.6560180187225342,"z":0.2761217951774597,"w":0.6474124789237976},"size":14.470815658569336,"orthographic":false}